odoo/addons/fieldservice_agreement/README.rst
odoo/addons/fieldservice_agreement/__init__.py
odoo/addons/fieldservice_agreement/__manifest__.py
odoo/addons/fieldservice_agreement/i18n/de.po
odoo/addons/fieldservice_agreement/i18n/es.po
odoo/addons/fieldservice_agreement/i18n/es_AR.po
odoo/addons/fieldservice_agreement/i18n/es_CL.po
odoo/addons/fieldservice_agreement/i18n/fieldservice_agreement.pot
odoo/addons/fieldservice_agreement/i18n/it.po
odoo/addons/fieldservice_agreement/i18n/pt_BR.po
odoo/addons/fieldservice_agreement/migrations/18.0.1.1.0/post-migrate.py
odoo/addons/fieldservice_agreement/models/__init__.py
odoo/addons/fieldservice_agreement/models/agreement.py
odoo/addons/fieldservice_agreement/models/fsm_equipment.py
odoo/addons/fieldservice_agreement/models/fsm_order.py
odoo/addons/fieldservice_agreement/models/fsm_person.py
odoo/addons/fieldservice_agreement/readme/CONFIGURE.md
odoo/addons/fieldservice_agreement/readme/CONTRIBUTORS.md
odoo/addons/fieldservice_agreement/readme/CREDITS.md
odoo/addons/fieldservice_agreement/readme/DESCRIPTION.md
odoo/addons/fieldservice_agreement/readme/ROADMAP.md
odoo/addons/fieldservice_agreement/readme/USAGE.md
odoo/addons/fieldservice_agreement/static/description/icon.png
odoo/addons/fieldservice_agreement/static/description/index.html
odoo/addons/fieldservice_agreement/tests/__init__.py
odoo/addons/fieldservice_agreement/tests/test_fsm_agreement.py
odoo/addons/fieldservice_agreement/views/agreement_view.xml
odoo/addons/fieldservice_agreement/views/fsm_equipment_view.xml
odoo/addons/fieldservice_agreement/views/fsm_order_view.xml
odoo/addons/fieldservice_agreement/views/fsm_person.xml
odoo_addon_fieldservice_agreement-18.0.2.0.1.2.dist-info/METADATA
odoo_addon_fieldservice_agreement-18.0.2.0.1.2.dist-info/WHEEL
odoo_addon_fieldservice_agreement-18.0.2.0.1.2.dist-info/top_level.txt
odoo_addon_fieldservice_agreement-18.0.2.0.1.2.dist-info/RECORD
